simple_keenetic_client/__init__.py
simple_keenetic_client-0.1.3.dist-info/LICENSE
simple_keenetic_client-0.1.3.dist-info/METADATA
simple_keenetic_client-0.1.3.dist-info/WHEEL
simple_keenetic_client-0.1.3.dist-info/RECORD
