Metadata-Version: 2.1
Name: simple-keenetic-client
Version: 0.1.3
Summary: Client for KeeneticOS-based routers via HTTP interface
License: MIT
Author: Leonid Amirov
Author-email: leonid.amirov@gmail.com
Requires-Python: >=3.11,<4.0
Classifier: License :: OSI Approved :: MIT License
Classifier: Programming Language :: Python :: 3
Classifier: Programming Language :: Python :: 3.11
Classifier: Programming Language :: Python :: 3.12
Requires-Dist: aiohttp (>=3.11.7,<4.0.0)
Project-URL: repository, https://github.com/side2k/simple-keenetic-client
